{
    "key": "group_66ce0b674e3e1",
    "title": "Block: Activities List",
    "fields": [
        {
            "key": "field_66ce0b67b3cc3",
            "label": "Padding Top",
            "name": "padding_top",
            "aria-label": "",
            "type": "range",
            "instructions": "",
            "required": 0,
            "conditional_logic": 0,
            "wrapper": {
                "width": "",
                "class": "",
                "id": ""
            },
            "default_value": 50,
            "min": "",
            "max": "",
            "step": "",
            "prepend": "",
            "append": ""
        },
        {
            "key": "field_66ce0ba1b3cc4",
            "label": "Padding Bottom",
            "name": "padding_bottom",
            "aria-label": "",
            "type": "range",
            "instructions": "",
            "required": 0,
            "conditional_logic": 0,
            "wrapper": {
                "width": "",
                "class": "",
                "id": ""
            },
            "default_value": 50,
            "min": "",
            "max": "",
            "step": "",
            "prepend": "",
            "append": ""
        },
        {
            "key": "field_66ce0dd21d495",
            "label": "Activities",
            "name": "activities",
            "aria-label": "",
            "type": "select",
            "instructions": "",
            "required": 0,
            "conditional_logic": 0,
            "wrapper": {
                "width": "",
                "class": "",
                "id": ""
            },
            "choices": {
                "day-camps": "Day Camp Activities",
                "overnight-camps": "Overnight Camp Activities",
                "schools-groups": "Schools & Groups"
            },
            "default_value": false,
            "return_format": "value",
            "multiple": 0,
            "allow_null": 0,
            "ui": 0,
            "ajax": 0,
            "placeholder": ""
        }
    ],
    "location": [
        [
            {
                "param": "block",
                "operator": "==",
                "value": "fcc\/activities-list"
            }
        ]
    ],
    "menu_order": 0,
    "position": "normal",
    "style": "default",
    "label_placement": "top",
    "instruction_placement": "label",
    "hide_on_screen": "",
    "active": true,
    "description": "",
    "show_in_rest": 0,
    "modified": 1724782624
}
